{
  "features": [
    {
      "id": "rogue-expertise-1",
      "slug": "rogue-expertise-1",
      "name": "rogue-expertise-1",
      "aliases": [
        "rogue-expertise-1",
        ""
      ],
      "source": "native",
      "source_bucket": "srd_or_original_summary",
      "rules_version": "5e2024-compatible",
      "class_id": "rogue",
      "subclass_id": null,
      "species_id": null,
      "feat_id": null,
      "background_id": null,
      "item_id": null,
      "level": 0,
      "kind": "class",
      "action_type": "passive",
      "activation_type": "passive",
      "trigger": "",
      "range": "",
      "duration": "",
      "concentration": false,
      "resource_name": "",
      "resource_cost": null,
      "uses_max": null,
      "uses_current": null,
      "uses_formula": "",
      "recovery": "none",
      "save_ability": "",
      "save_dc_formula": "",
      "attack_bonus_formula": "",
      "damage_formula": "",
      "healing_formula": "",
      "damage_type": "",
      "scaling": {},
      "grants_actions": [],
      "grants_spells": [],
      "grants_proficiencies": [],
      "grants_resistances": [],
      "grants_immunities": [],
      "grants_senses": [],
      "grants_movement": {},
      "grants_ac_formula": "",
      "grants_stat_override": {},
      "grants_advantage": [],
      "grants_disadvantage": [],
      "roll_buttons": [],
      "runtime_hooks": [],
      "safe_summary": "Choose 2 skills or tools you are proficient in and double your proficiency bonus for those checks.",
      "rules_summary": "Choose 2 skills or tools you are proficient in and double your proficiency bonus for those checks.",
      "play_advice": "",
      "needs_review": false,
      "implementation_status": "structured"
    },
    {
      "id": "rogue-sneak-attack-1d6",
      "slug": "rogue-sneak-attack-1d6",
      "name": "rogue-sneak-attack-1d6",
      "aliases": [
        "rogue-sneak-attack-1d6",
        ""
      ],
      "source": "native",
      "source_bucket": "srd_or_original_summary",
      "rules_version": "5e2024-compatible",
      "class_id": "rogue",
      "subclass_id": null,
      "species_id": null,
      "feat_id": null,
      "background_id": null,
      "item_id": null,
      "level": 0,
      "kind": "class",
      "action_type": "passive",
      "activation_type": "passive",
      "trigger": "",
      "range": "",
      "duration": "",
      "concentration": false,
      "resource_name": "",
      "resource_cost": null,
      "uses_max": null,
      "uses_current": null,
      "uses_formula": "",
      "recovery": "none",
      "save_ability": "",
      "save_dc_formula": "",
      "attack_bonus_formula": "",
      "damage_formula": "",
      "healing_formula": "",
      "damage_type": "",
      "scaling": {},
      "grants_actions": [],
      "grants_spells": [],
      "grants_proficiencies": [],
      "grants_resistances": [],
      "grants_immunities": [],
      "grants_senses": [],
      "grants_movement": {},
      "grants_ac_formula": "",
      "grants_stat_override": {},
      "grants_advantage": [],
      "grants_disadvantage": [],
      "roll_buttons": [],
      "runtime_hooks": [],
      "safe_summary": "Once per turn, deal 1d6 extra damage when you hit with a Finesse or ranged weapon and have Advantage or a nearby ally.",
      "rules_summary": "Once per turn, deal 1d6 extra damage when you hit with a Finesse or ranged weapon and have Advantage or a nearby ally.",
      "play_advice": "",
      "needs_review": false,
      "implementation_status": "structured"
    },
    {
      "id": "rogue-thieves-cant",
      "slug": "rogue-thieves-cant",
      "name": "rogue-thieves-cant",
      "aliases": [
        "rogue-thieves-cant",
        ""
      ],
      "source": "native",
      "source_bucket": "srd_or_original_summary",
      "rules_version": "5e2024-compatible",
      "class_id": "rogue",
      "subclass_id": null,
      "species_id": null,
      "feat_id": null,
      "background_id": null,
      "item_id": null,
      "level": 0,
      "kind": "class",
      "action_type": "passive",
      "activation_type": "passive",
      "trigger": "",
      "range": "",
      "duration": "",
      "concentration": false,
      "resource_name": "",
      "resource_cost": null,
      "uses_max": null,
      "uses_current": null,
      "uses_formula": "",
      "recovery": "none",
      "save_ability": "",
      "save_dc_formula": "",
      "attack_bonus_formula": "",
      "damage_formula": "",
      "healing_formula": "",
      "damage_type": "",
      "scaling": {},
      "grants_actions": [],
      "grants_spells": [],
      "grants_proficiencies": [],
      "grants_resistances": [],
      "grants_immunities": [],
      "grants_senses": [],
      "grants_movement": {},
      "grants_ac_formula": "",
      "grants_stat_override": {},
      "grants_advantage": [],
      "grants_disadvantage": [],
      "roll_buttons": [],
      "runtime_hooks": [],
      "safe_summary": "You know the secret language and signs of the criminal underworld, and can pass hidden messages through ordinary conversation.",
      "rules_summary": "You know the secret language and signs of the criminal underworld, and can pass hidden messages through ordinary conversation.",
      "play_advice": "",
      "needs_review": false,
      "implementation_status": "structured"
    },
    {
      "id": "rogue-cunning-action",
      "slug": "rogue-cunning-action",
      "name": "rogue-cunning-action",
      "aliases": [
        "rogue-cunning-action",
        ""
      ],
      "source": "native",
      "source_bucket": "srd_or_original_summary",
      "rules_version": "5e2024-compatible",
      "class_id": "rogue",
      "subclass_id": null,
      "species_id": null,
      "feat_id": null,
      "background_id": null,
      "item_id": null,
      "level": 0,
      "kind": "class",
      "action_type": "bonus_action",
      "activation_type": "bonus_action",
      "trigger": "",
      "range": "",
      "duration": "",
      "concentration": false,
      "resource_name": "",
      "resource_cost": null,
      "uses_max": null,
      "uses_current": null,
      "uses_formula": "",
      "recovery": "none",
      "save_ability": "",
      "save_dc_formula": "",
      "attack_bonus_formula": "",
      "damage_formula": "",
      "healing_formula": "",
      "damage_type": "",
      "scaling": {},
      "grants_actions": [
        {
          "id": "rogue-cunning-action-action",
          "name": "rogue-cunning-action",
          "action_type": "bonus_action",
          "resource_name": "",
          "summary": "Use your Bonus Action to Dash, Disengage, or Hide on every turn."
        }
      ],
      "grants_spells": [],
      "grants_proficiencies": [],
      "grants_resistances": [],
      "grants_immunities": [],
      "grants_senses": [],
      "grants_movement": {},
      "grants_ac_formula": "",
      "grants_stat_override": {},
      "grants_advantage": [],
      "grants_disadvantage": [],
      "roll_buttons": [],
      "runtime_hooks": [],
      "safe_summary": "Use your Bonus Action to Dash, Disengage, or Hide on every turn.",
      "rules_summary": "Use your Bonus Action to Dash, Disengage, or Hide on every turn.",
      "play_advice": "",
      "needs_review": false,
      "implementation_status": "structured"
    },
    {
      "id": "rogue-roguish-archetype-subclass",
      "slug": "rogue-roguish-archetype-subclass",
      "name": "rogue-roguish-archetype-subclass",
      "aliases": [
        "rogue-roguish-archetype-subclass",
        ""
      ],
      "source": "native",
      "source_bucket": "srd_or_original_summary",
      "rules_version": "5e2024-compatible",
      "class_id": "rogue",
      "subclass_id": null,
      "species_id": null,
      "feat_id": null,
      "background_id": null,
      "item_id": null,
      "level": 0,
      "kind": "class",
      "action_type": "passive",
      "activation_type": "passive",
      "trigger": "",
      "range": "",
      "duration": "",
      "concentration": false,
      "resource_name": "",
      "resource_cost": null,
      "uses_max": null,
      "uses_current": null,
      "uses_formula": "",
      "recovery": "none",
      "save_ability": "",
      "save_dc_formula": "",
      "attack_bonus_formula": "",
      "damage_formula": "",
      "healing_formula": "",
      "damage_type": "",
      "scaling": {},
      "grants_actions": [],
      "grants_spells": [],
      "grants_proficiencies": [],
      "grants_resistances": [],
      "grants_immunities": [],
      "grants_senses": [],
      "grants_movement": {},
      "grants_ac_formula": "",
      "grants_stat_override": {},
      "grants_advantage": [],
      "grants_disadvantage": [],
      "roll_buttons": [],
      "runtime_hooks": [],
      "safe_summary": "Choose your Roguish Archetype subclass, which grants you specialized features at levels 3, 9, 13, and 17.",
      "rules_summary": "Choose your Roguish Archetype subclass, which grants you specialized features at levels 3, 9, 13, and 17.",
      "play_advice": "",
      "needs_review": false,
      "implementation_status": "structured"
    },
    {
      "id": "rogue-steady-aim",
      "slug": "rogue-steady-aim",
      "name": "rogue-steady-aim",
      "aliases": [
        "rogue-steady-aim",
        ""
      ],
      "source": "native",
      "source_bucket": "srd_or_original_summary",
      "rules_version": "5e2024-compatible",
      "class_id": "rogue",
      "subclass_id": null,
      "species_id": null,
      "feat_id": null,
      "background_id": null,
      "item_id": null,
      "level": 0,
      "kind": "class",
      "action_type": "bonus_action",
      "activation_type": "bonus_action",
      "trigger": "",
      "range": "",
      "duration": "",
      "concentration": false,
      "resource_name": "",
      "resource_cost": null,
      "uses_max": null,
      "uses_current": null,
      "uses_formula": "",
      "recovery": "none",
      "save_ability": "",
      "save_dc_formula": "",
      "attack_bonus_formula": "",
      "damage_formula": "",
      "healing_formula": "",
      "damage_type": "",
      "scaling": {},
      "grants_actions": [
        {
          "id": "rogue-steady-aim-action",
          "name": "rogue-steady-aim",
          "action_type": "bonus_action",
          "resource_name": "",
          "summary": "Use your Bonus Action to give yourself Advantage on your next attack this turn; your Speed becomes 0 until the end of the turn."
        }
      ],
      "grants_spells": [],
      "grants_proficiencies": [],
      "grants_resistances": [],
      "grants_immunities": [],
      "grants_senses": [],
      "grants_movement": {},
      "grants_ac_formula": "",
      "grants_stat_override": {},
      "grants_advantage": [],
      "grants_disadvantage": [],
      "roll_buttons": [],
      "runtime_hooks": [],
      "safe_summary": "Use your Bonus Action to give yourself Advantage on your next attack this turn; your Speed becomes 0 until the end of the turn.",
      "rules_summary": "Use your Bonus Action to give yourself Advantage on your next attack this turn; your Speed becomes 0 until the end of the turn.",
      "play_advice": "",
      "needs_review": false,
      "implementation_status": "structured"
    },
    {
      "id": "rogue-cunning-strike",
      "slug": "rogue-cunning-strike",
      "name": "rogue-cunning-strike",
      "aliases": [
        "rogue-cunning-strike",
        ""
      ],
      "source": "native",
      "source_bucket": "srd_or_original_summary",
      "rules_version": "5e2024-compatible",
      "class_id": "rogue",
      "subclass_id": null,
      "species_id": null,
      "feat_id": null,
      "background_id": null,
      "item_id": null,
      "level": 0,
      "kind": "class",
      "action_type": "passive",
      "activation_type": "passive",
      "trigger": "",
      "range": "",
      "duration": "",
      "concentration": false,
      "resource_name": "",
      "resource_cost": null,
      "uses_max": null,
      "uses_current": null,
      "uses_formula": "",
      "recovery": "none",
      "save_ability": "",
      "save_dc_formula": "",
      "attack_bonus_formula": "",
      "damage_formula": "",
      "healing_formula": "",
      "damage_type": "",
      "scaling": {},
      "grants_actions": [],
      "grants_spells": [],
      "grants_proficiencies": [],
      "grants_resistances": [],
      "grants_immunities": [],
      "grants_senses": [],
      "grants_movement": {},
      "grants_ac_formula": "",
      "grants_stat_override": {},
      "grants_advantage": [],
      "grants_disadvantage": [],
      "roll_buttons": [],
      "runtime_hooks": [],
      "safe_summary": "When you deal Sneak Attack damage, forgo 1d6 of it to impose a bonus effect on the target.",
      "rules_summary": "When you deal Sneak Attack damage, forgo 1d6 of it to impose a bonus effect on the target.",
      "play_advice": "",
      "needs_review": false,
      "implementation_status": "structured"
    },
    {
      "id": "rogue-evasion",
      "slug": "rogue-evasion",
      "name": "rogue-evasion",
      "aliases": [
        "rogue-evasion",
        ""
      ],
      "source": "native",
      "source_bucket": "srd_or_original_summary",
      "rules_version": "5e2024-compatible",
      "class_id": "rogue",
      "subclass_id": null,
      "species_id": null,
      "feat_id": null,
      "background_id": null,
      "item_id": null,
      "level": 0,
      "kind": "class",
      "action_type": "passive",
      "activation_type": "passive",
      "trigger": "",
      "range": "",
      "duration": "",
      "concentration": false,
      "resource_name": "",
      "resource_cost": null,
      "uses_max": null,
      "uses_current": null,
      "uses_formula": "",
      "recovery": "none",
      "save_ability": "",
      "save_dc_formula": "",
      "attack_bonus_formula": "",
      "damage_formula": "",
      "healing_formula": "",
      "damage_type": "",
      "scaling": {},
      "grants_actions": [],
      "grants_spells": [],
      "grants_proficiencies": [],
      "grants_resistances": [],
      "grants_immunities": [],
      "grants_senses": [],
      "grants_movement": {},
      "grants_ac_formula": "",
      "grants_stat_override": {},
      "grants_advantage": [],
      "grants_disadvantage": [],
      "roll_buttons": [],
      "runtime_hooks": [],
      "safe_summary": "When an effect lets you make a Dexterity saving throw for half damage, you take no damage on a success and only half on a failure.",
      "rules_summary": "When an effect lets you make a Dexterity saving throw for half damage, you take no damage on a success and only half on a failure.",
      "play_advice": "",
      "needs_review": false,
      "implementation_status": "structured"
    },
    {
      "id": "rogue-reliable-talent",
      "slug": "rogue-reliable-talent",
      "name": "rogue-reliable-talent",
      "aliases": [
        "rogue-reliable-talent",
        ""
      ],
      "source": "native",
      "source_bucket": "srd_or_original_summary",
      "rules_version": "5e2024-compatible",
      "class_id": "rogue",
      "subclass_id": null,
      "species_id": null,
      "feat_id": null,
      "background_id": null,
      "item_id": null,
      "level": 0,
      "kind": "class",
      "action_type": "passive",
      "activation_type": "passive",
      "trigger": "",
      "range": "",
      "duration": "",
      "concentration": false,
      "resource_name": "",
      "resource_cost": null,
      "uses_max": null,
      "uses_current": null,
      "uses_formula": "",
      "recovery": "none",
      "save_ability": "",
      "save_dc_formula": "",
      "attack_bonus_formula": "",
      "damage_formula": "",
      "healing_formula": "",
      "damage_type": "",
      "scaling": {},
      "grants_actions": [],
      "grants_spells": [],
      "grants_proficiencies": [],
      "grants_resistances": [],
      "grants_immunities": [],
      "grants_senses": [],
      "grants_movement": {},
      "grants_ac_formula": "",
      "grants_stat_override": {},
      "grants_advantage": [],
      "grants_disadvantage": [],
      "roll_buttons": [],
      "runtime_hooks": [],
      "safe_summary": "When you make an ability check using a skill or tool you are proficient in, treat any d20 roll of 9 or lower as a 10.",
      "rules_summary": "When you make an ability check using a skill or tool you are proficient in, treat any d20 roll of 9 or lower as a 10.",
      "play_advice": "",
      "needs_review": false,
      "implementation_status": "structured"
    },
    {
      "id": "rogue-improved-cunning-strike",
      "slug": "rogue-improved-cunning-strike",
      "name": "rogue-improved-cunning-strike",
      "aliases": [
        "rogue-improved-cunning-strike",
        ""
      ],
      "source": "native",
      "source_bucket": "srd_or_original_summary",
      "rules_version": "5e2024-compatible",
      "class_id": "rogue",
      "subclass_id": null,
      "species_id": null,
      "feat_id": null,
      "background_id": null,
      "item_id": null,
      "level": 0,
      "kind": "class",
      "action_type": "passive",
      "activation_type": "passive",
      "trigger": "",
      "range": "",
      "duration": "",
      "concentration": false,
      "resource_name": "",
      "resource_cost": null,
      "uses_max": null,
      "uses_current": null,
      "uses_formula": "",
      "recovery": "none",
      "save_ability": "",
      "save_dc_formula": "",
      "attack_bonus_formula": "",
      "damage_formula": "",
      "healing_formula": "",
      "damage_type": "",
      "scaling": {},
      "grants_actions": [],
      "grants_spells": [],
      "grants_proficiencies": [],
      "grants_resistances": [],
      "grants_immunities": [],
      "grants_senses": [],
      "grants_movement": {},
      "grants_ac_formula": "",
      "grants_stat_override": {},
      "grants_advantage": [],
      "grants_disadvantage": [],
      "roll_buttons": [],
      "runtime_hooks": [],
      "safe_summary": "You can now apply two Cunning Strike effects on the same Sneak Attack, paying both dice costs.",
      "rules_summary": "You can now apply two Cunning Strike effects on the same Sneak Attack, paying both dice costs.",
      "play_advice": "",
      "needs_review": false,
      "implementation_status": "structured"
    },
    {
      "id": "rogue-devious-strikes",
      "slug": "rogue-devious-strikes",
      "name": "rogue-devious-strikes",
      "aliases": [
        "rogue-devious-strikes",
        ""
      ],
      "source": "native",
      "source_bucket": "srd_or_original_summary",
      "rules_version": "5e2024-compatible",
      "class_id": "rogue",
      "subclass_id": null,
      "species_id": null,
      "feat_id": null,
      "background_id": null,
      "item_id": null,
      "level": 0,
      "kind": "class",
      "action_type": "passive",
      "activation_type": "passive",
      "trigger": "",
      "range": "",
      "duration": "",
      "concentration": false,
      "resource_name": "",
      "resource_cost": null,
      "uses_max": null,
      "uses_current": null,
      "uses_formula": "",
      "recovery": "none",
      "save_ability": "",
      "save_dc_formula": "",
      "attack_bonus_formula": "",
      "damage_formula": "",
      "healing_formula": "",
      "damage_type": "",
      "scaling": {},
      "grants_actions": [],
      "grants_spells": [],
      "grants_proficiencies": [],
      "grants_resistances": [],
      "grants_immunities": [],
      "grants_senses": [],
      "grants_movement": {},
      "grants_ac_formula": "",
      "grants_stat_override": {},
      "grants_advantage": [],
      "grants_disadvantage": [],
      "roll_buttons": [],
      "runtime_hooks": [],
      "safe_summary": "Gain three new, more powerful Cunning Strike options: Daze, Knock Out, and Obscure.",
      "rules_summary": "Gain three new, more powerful Cunning Strike options: Daze, Knock Out, and Obscure.",
      "play_advice": "",
      "needs_review": false,
      "implementation_status": "structured"
    },
    {
      "id": "rogue-slippery-mind",
      "slug": "rogue-slippery-mind",
      "name": "rogue-slippery-mind",
      "aliases": [
        "rogue-slippery-mind",
        ""
      ],
      "source": "native",
      "source_bucket": "srd_or_original_summary",
      "rules_version": "5e2024-compatible",
      "class_id": "rogue",
      "subclass_id": null,
      "species_id": null,
      "feat_id": null,
      "background_id": null,
      "item_id": null,
      "level": 0,
      "kind": "class",
      "action_type": "passive",
      "activation_type": "passive",
      "trigger": "",
      "range": "",
      "duration": "",
      "concentration": false,
      "resource_name": "",
      "resource_cost": null,
      "uses_max": null,
      "uses_current": null,
      "uses_formula": "",
      "recovery": "none",
      "save_ability": "",
      "save_dc_formula": "",
      "attack_bonus_formula": "",
      "damage_formula": "",
      "healing_formula": "",
      "damage_type": "",
      "scaling": {},
      "grants_actions": [],
      "grants_spells": [],
      "grants_proficiencies": [],
      "grants_resistances": [],
      "grants_immunities": [],
      "grants_senses": [],
      "grants_movement": {},
      "grants_ac_formula": "",
      "grants_stat_override": {},
      "grants_advantage": [],
      "grants_disadvantage": [],
      "roll_buttons": [],
      "runtime_hooks": [],
      "safe_summary": "You gain proficiency in Wisdom saving throws and Intelligence saving throws.",
      "rules_summary": "You gain proficiency in Wisdom saving throws and Intelligence saving throws.",
      "play_advice": "",
      "needs_review": false,
      "implementation_status": "structured"
    },
    {
      "id": "rogue-subtle-strikes",
      "slug": "rogue-subtle-strikes",
      "name": "rogue-subtle-strikes",
      "aliases": [
        "rogue-subtle-strikes",
        ""
      ],
      "source": "native",
      "source_bucket": "srd_or_original_summary",
      "rules_version": "5e2024-compatible",
      "class_id": "rogue",
      "subclass_id": null,
      "species_id": null,
      "feat_id": null,
      "background_id": null,
      "item_id": null,
      "level": 0,
      "kind": "class",
      "action_type": "passive",
      "activation_type": "passive",
      "trigger": "",
      "range": "",
      "duration": "",
      "concentration": false,
      "resource_name": "",
      "resource_cost": null,
      "uses_max": null,
      "uses_current": null,
      "uses_formula": "",
      "recovery": "none",
      "save_ability": "",
      "save_dc_formula": "",
      "attack_bonus_formula": "",
      "damage_formula": "",
      "healing_formula": "",
      "damage_type": "",
      "scaling": {},
      "grants_actions": [],
      "grants_spells": [],
      "grants_proficiencies": [],
      "grants_resistances": [],
      "grants_immunities": [],
      "grants_senses": [],
      "grants_movement": {},
      "grants_ac_formula": "",
      "grants_stat_override": {},
      "grants_advantage": [],
      "grants_disadvantage": [],
      "roll_buttons": [],
      "runtime_hooks": [],
      "safe_summary": "When an ally is within 5 feet of a creature, you have Advantage on your attacks against that creature even if you have a source of Disadvantage.",
      "rules_summary": "When an ally is within 5 feet of a creature, you have Advantage on your attacks against that creature even if you have a source of Disadvantage.",
      "play_advice": "",
      "needs_review": false,
      "implementation_status": "structured"
    },
    {
      "id": "rogue-elusive",
      "slug": "rogue-elusive",
      "name": "rogue-elusive",
      "aliases": [
        "rogue-elusive",
        ""
      ],
      "source": "native",
      "source_bucket": "srd_or_original_summary",
      "rules_version": "5e2024-compatible",
      "class_id": "rogue",
      "subclass_id": null,
      "species_id": null,
      "feat_id": null,
      "background_id": null,
      "item_id": null,
      "level": 0,
      "kind": "class",
      "action_type": "passive",
      "activation_type": "passive",
      "trigger": "",
      "range": "",
      "duration": "",
      "concentration": false,
      "resource_name": "",
      "resource_cost": null,
      "uses_max": null,
      "uses_current": null,
      "uses_formula": "",
      "recovery": "none",
      "save_ability": "",
      "save_dc_formula": "",
      "attack_bonus_formula": "",
      "damage_formula": "",
      "healing_formula": "",
      "damage_type": "",
      "scaling": {},
      "grants_actions": [],
      "grants_spells": [],
      "grants_proficiencies": [],
      "grants_resistances": [],
      "grants_immunities": [],
      "grants_senses": [],
      "grants_movement": {},
      "grants_ac_formula": "",
      "grants_stat_override": {},
      "grants_advantage": [],
      "grants_disadvantage": [],
      "roll_buttons": [],
      "runtime_hooks": [],
      "safe_summary": "No attack roll has Advantage against you while you are not Incapacitated.",
      "rules_summary": "No attack roll has Advantage against you while you are not Incapacitated.",
      "play_advice": "",
      "needs_review": false,
      "implementation_status": "structured"
    },
    {
      "id": "rogue-stroke-of-luck",
      "slug": "rogue-stroke-of-luck",
      "name": "rogue-stroke-of-luck",
      "aliases": [
        "rogue-stroke-of-luck",
        ""
      ],
      "source": "native",
      "source_bucket": "srd_or_original_summary",
      "rules_version": "5e2024-compatible",
      "class_id": "rogue",
      "subclass_id": null,
      "species_id": null,
      "feat_id": null,
      "background_id": null,
      "item_id": null,
      "level": 0,
      "kind": "class",
      "action_type": "passive",
      "activation_type": "passive",
      "trigger": "",
      "range": "",
      "duration": "",
      "concentration": false,
      "resource_name": "",
      "resource_cost": null,
      "uses_max": null,
      "uses_current": null,
      "uses_formula": "",
      "recovery": "none",
      "save_ability": "",
      "save_dc_formula": "",
      "attack_bonus_formula": "",
      "damage_formula": "",
      "healing_formula": "",
      "damage_type": "",
      "scaling": {},
      "grants_actions": [],
      "grants_spells": [],
      "grants_proficiencies": [],
      "grants_resistances": [],
      "grants_immunities": [],
      "grants_senses": [],
      "grants_movement": {},
      "grants_ac_formula": "",
      "grants_stat_override": {},
      "grants_advantage": [],
      "grants_disadvantage": [],
      "roll_buttons": [],
      "runtime_hooks": [],
      "safe_summary": "Once per Short or Long Rest, treat a missed attack or failed ability check as though you rolled a 20 on the d20.",
      "rules_summary": "Once per Short or Long Rest, treat a missed attack or failed ability check as though you rolled a 20 on the d20.",
      "play_advice": "",
      "needs_review": false,
      "implementation_status": "structured"
    },
    {
      "id": "rogue-expertise-2",
      "slug": "rogue-expertise-2",
      "name": "rogue-expertise-2",
      "aliases": [
        "rogue-expertise-2",
        ""
      ],
      "source": "native",
      "source_bucket": "srd_or_original_summary",
      "rules_version": "5e2024-compatible",
      "class_id": "rogue",
      "subclass_id": null,
      "species_id": null,
      "feat_id": null,
      "background_id": null,
      "item_id": null,
      "level": 0,
      "kind": "class",
      "action_type": "passive",
      "activation_type": "passive",
      "trigger": "",
      "range": "",
      "duration": "",
      "concentration": false,
      "resource_name": "",
      "resource_cost": null,
      "uses_max": null,
      "uses_current": null,
      "uses_formula": "",
      "recovery": "none",
      "save_ability": "",
      "save_dc_formula": "",
      "attack_bonus_formula": "",
      "damage_formula": "",
      "healing_formula": "",
      "damage_type": "",
      "scaling": {},
      "grants_actions": [],
      "grants_spells": [],
      "grants_proficiencies": [],
      "grants_resistances": [],
      "grants_immunities": [],
      "grants_senses": [],
      "grants_movement": {},
      "grants_ac_formula": "",
      "grants_stat_override": {},
      "grants_advantage": [],
      "grants_disadvantage": [],
      "roll_buttons": [],
      "runtime_hooks": [],
      "safe_summary": "Choose 2 more skills or tools you are proficient in and double your proficiency bonus for those checks.",
      "rules_summary": "Choose 2 more skills or tools you are proficient in and double your proficiency bonus for those checks.",
      "play_advice": "",
      "needs_review": false,
      "implementation_status": "structured"
    },
    {
      "id": "rogue-sneak-attack-l3",
      "slug": "rogue-sneak-attack-l3",
      "name": "rogue-sneak-attack-l3",
      "aliases": [
        "rogue-sneak-attack-l3",
        ""
      ],
      "source": "native",
      "source_bucket": "srd_or_original_summary",
      "rules_version": "5e2024-compatible",
      "class_id": "rogue",
      "subclass_id": null,
      "species_id": null,
      "feat_id": null,
      "background_id": null,
      "item_id": null,
      "level": 0,
      "kind": "class",
      "action_type": "passive",
      "activation_type": "passive",
      "trigger": "",
      "range": "",
      "duration": "",
      "concentration": false,
      "resource_name": "",
      "resource_cost": null,
      "uses_max": null,
      "uses_current": null,
      "uses_formula": "",
      "recovery": "none",
      "save_ability": "",
      "save_dc_formula": "",
      "attack_bonus_formula": "",
      "damage_formula": "",
      "healing_formula": "",
      "damage_type": "",
      "scaling": {},
      "grants_actions": [],
      "grants_spells": [],
      "grants_proficiencies": [],
      "grants_resistances": [],
      "grants_immunities": [],
      "grants_senses": [],
      "grants_movement": {},
      "grants_ac_formula": "",
      "grants_stat_override": {},
      "grants_advantage": [],
      "grants_disadvantage": [],
      "roll_buttons": [],
      "runtime_hooks": [],
      "safe_summary": "Your Sneak Attack damage increases to 2d6.",
      "rules_summary": "Your Sneak Attack damage increases to 2d6.",
      "play_advice": "",
      "needs_review": false,
      "implementation_status": "structured"
    },
    {
      "id": "rogue-sneak-attack-l5",
      "slug": "rogue-sneak-attack-l5",
      "name": "rogue-sneak-attack-l5",
      "aliases": [
        "rogue-sneak-attack-l5",
        ""
      ],
      "source": "native",
      "source_bucket": "srd_or_original_summary",
      "rules_version": "5e2024-compatible",
      "class_id": "rogue",
      "subclass_id": null,
      "species_id": null,
      "feat_id": null,
      "background_id": null,
      "item_id": null,
      "level": 0,
      "kind": "class",
      "action_type": "passive",
      "activation_type": "passive",
      "trigger": "",
      "range": "",
      "duration": "",
      "concentration": false,
      "resource_name": "",
      "resource_cost": null,
      "uses_max": null,
      "uses_current": null,
      "uses_formula": "",
      "recovery": "none",
      "save_ability": "",
      "save_dc_formula": "",
      "attack_bonus_formula": "",
      "damage_formula": "",
      "healing_formula": "",
      "damage_type": "",
      "scaling": {},
      "grants_actions": [],
      "grants_spells": [],
      "grants_proficiencies": [],
      "grants_resistances": [],
      "grants_immunities": [],
      "grants_senses": [],
      "grants_movement": {},
      "grants_ac_formula": "",
      "grants_stat_override": {},
      "grants_advantage": [],
      "grants_disadvantage": [],
      "roll_buttons": [],
      "runtime_hooks": [],
      "safe_summary": "Your Sneak Attack damage increases to 3d6.",
      "rules_summary": "Your Sneak Attack damage increases to 3d6.",
      "play_advice": "",
      "needs_review": false,
      "implementation_status": "structured"
    },
    {
      "id": "rogue-sneak-attack-l7",
      "slug": "rogue-sneak-attack-l7",
      "name": "rogue-sneak-attack-l7",
      "aliases": [
        "rogue-sneak-attack-l7",
        ""
      ],
      "source": "native",
      "source_bucket": "srd_or_original_summary",
      "rules_version": "5e2024-compatible",
      "class_id": "rogue",
      "subclass_id": null,
      "species_id": null,
      "feat_id": null,
      "background_id": null,
      "item_id": null,
      "level": 0,
      "kind": "class",
      "action_type": "passive",
      "activation_type": "passive",
      "trigger": "",
      "range": "",
      "duration": "",
      "concentration": false,
      "resource_name": "",
      "resource_cost": null,
      "uses_max": null,
      "uses_current": null,
      "uses_formula": "",
      "recovery": "none",
      "save_ability": "",
      "save_dc_formula": "",
      "attack_bonus_formula": "",
      "damage_formula": "",
      "healing_formula": "",
      "damage_type": "",
      "scaling": {},
      "grants_actions": [],
      "grants_spells": [],
      "grants_proficiencies": [],
      "grants_resistances": [],
      "grants_immunities": [],
      "grants_senses": [],
      "grants_movement": {},
      "grants_ac_formula": "",
      "grants_stat_override": {},
      "grants_advantage": [],
      "grants_disadvantage": [],
      "roll_buttons": [],
      "runtime_hooks": [],
      "safe_summary": "Your Sneak Attack damage increases to 4d6.",
      "rules_summary": "Your Sneak Attack damage increases to 4d6.",
      "play_advice": "",
      "needs_review": false,
      "implementation_status": "structured"
    },
    {
      "id": "rogue-sneak-attack-l9",
      "slug": "rogue-sneak-attack-l9",
      "name": "rogue-sneak-attack-l9",
      "aliases": [
        "rogue-sneak-attack-l9",
        ""
      ],
      "source": "native",
      "source_bucket": "srd_or_original_summary",
      "rules_version": "5e2024-compatible",
      "class_id": "rogue",
      "subclass_id": null,
      "species_id": null,
      "feat_id": null,
      "background_id": null,
      "item_id": null,
      "level": 0,
      "kind": "class",
      "action_type": "passive",
      "activation_type": "passive",
      "trigger": "",
      "range": "",
      "duration": "",
      "concentration": false,
      "resource_name": "",
      "resource_cost": null,
      "uses_max": null,
      "uses_current": null,
      "uses_formula": "",
      "recovery": "none",
      "save_ability": "",
      "save_dc_formula": "",
      "attack_bonus_formula": "",
      "damage_formula": "",
      "healing_formula": "",
      "damage_type": "",
      "scaling": {},
      "grants_actions": [],
      "grants_spells": [],
      "grants_proficiencies": [],
      "grants_resistances": [],
      "grants_immunities": [],
      "grants_senses": [],
      "grants_movement": {},
      "grants_ac_formula": "",
      "grants_stat_override": {},
      "grants_advantage": [],
      "grants_disadvantage": [],
      "roll_buttons": [],
      "runtime_hooks": [],
      "safe_summary": "Your Sneak Attack damage increases to 5d6.",
      "rules_summary": "Your Sneak Attack damage increases to 5d6.",
      "play_advice": "",
      "needs_review": false,
      "implementation_status": "structured"
    },
    {
      "id": "rogue-sneak-attack-l11",
      "slug": "rogue-sneak-attack-l11",
      "name": "rogue-sneak-attack-l11",
      "aliases": [
        "rogue-sneak-attack-l11",
        ""
      ],
      "source": "native",
      "source_bucket": "srd_or_original_summary",
      "rules_version": "5e2024-compatible",
      "class_id": "rogue",
      "subclass_id": null,
      "species_id": null,
      "feat_id": null,
      "background_id": null,
      "item_id": null,
      "level": 0,
      "kind": "class",
      "action_type": "passive",
      "activation_type": "passive",
      "trigger": "",
      "range": "",
      "duration": "",
      "concentration": false,
      "resource_name": "",
      "resource_cost": null,
      "uses_max": null,
      "uses_current": null,
      "uses_formula": "",
      "recovery": "none",
      "save_ability": "",
      "save_dc_formula": "",
      "attack_bonus_formula": "",
      "damage_formula": "",
      "healing_formula": "",
      "damage_type": "",
      "scaling": {},
      "grants_actions": [],
      "grants_spells": [],
      "grants_proficiencies": [],
      "grants_resistances": [],
      "grants_immunities": [],
      "grants_senses": [],
      "grants_movement": {},
      "grants_ac_formula": "",
      "grants_stat_override": {},
      "grants_advantage": [],
      "grants_disadvantage": [],
      "roll_buttons": [],
      "runtime_hooks": [],
      "safe_summary": "Your Sneak Attack damage increases to 6d6.",
      "rules_summary": "Your Sneak Attack damage increases to 6d6.",
      "play_advice": "",
      "needs_review": false,
      "implementation_status": "structured"
    },
    {
      "id": "rogue-sneak-attack-l13",
      "slug": "rogue-sneak-attack-l13",
      "name": "rogue-sneak-attack-l13",
      "aliases": [
        "rogue-sneak-attack-l13",
        ""
      ],
      "source": "native",
      "source_bucket": "srd_or_original_summary",
      "rules_version": "5e2024-compatible",
      "class_id": "rogue",
      "subclass_id": null,
      "species_id": null,
      "feat_id": null,
      "background_id": null,
      "item_id": null,
      "level": 0,
      "kind": "class",
      "action_type": "passive",
      "activation_type": "passive",
      "trigger": "",
      "range": "",
      "duration": "",
      "concentration": false,
      "resource_name": "",
      "resource_cost": null,
      "uses_max": null,
      "uses_current": null,
      "uses_formula": "",
      "recovery": "none",
      "save_ability": "",
      "save_dc_formula": "",
      "attack_bonus_formula": "",
      "damage_formula": "",
      "healing_formula": "",
      "damage_type": "",
      "scaling": {},
      "grants_actions": [],
      "grants_spells": [],
      "grants_proficiencies": [],
      "grants_resistances": [],
      "grants_immunities": [],
      "grants_senses": [],
      "grants_movement": {},
      "grants_ac_formula": "",
      "grants_stat_override": {},
      "grants_advantage": [],
      "grants_disadvantage": [],
      "roll_buttons": [],
      "runtime_hooks": [],
      "safe_summary": "Your Sneak Attack damage increases to 7d6.",
      "rules_summary": "Your Sneak Attack damage increases to 7d6.",
      "play_advice": "",
      "needs_review": false,
      "implementation_status": "structured"
    },
    {
      "id": "rogue-sneak-attack-l15",
      "slug": "rogue-sneak-attack-l15",
      "name": "rogue-sneak-attack-l15",
      "aliases": [
        "rogue-sneak-attack-l15",
        ""
      ],
      "source": "native",
      "source_bucket": "srd_or_original_summary",
      "rules_version": "5e2024-compatible",
      "class_id": "rogue",
      "subclass_id": null,
      "species_id": null,
      "feat_id": null,
      "background_id": null,
      "item_id": null,
      "level": 0,
      "kind": "class",
      "action_type": "passive",
      "activation_type": "passive",
      "trigger": "",
      "range": "",
      "duration": "",
      "concentration": false,
      "resource_name": "",
      "resource_cost": null,
      "uses_max": null,
      "uses_current": null,
      "uses_formula": "",
      "recovery": "none",
      "save_ability": "",
      "save_dc_formula": "",
      "attack_bonus_formula": "",
      "damage_formula": "",
      "healing_formula": "",
      "damage_type": "",
      "scaling": {},
      "grants_actions": [],
      "grants_spells": [],
      "grants_proficiencies": [],
      "grants_resistances": [],
      "grants_immunities": [],
      "grants_senses": [],
      "grants_movement": {},
      "grants_ac_formula": "",
      "grants_stat_override": {},
      "grants_advantage": [],
      "grants_disadvantage": [],
      "roll_buttons": [],
      "runtime_hooks": [],
      "safe_summary": "Your Sneak Attack damage increases to 8d6.",
      "rules_summary": "Your Sneak Attack damage increases to 8d6.",
      "play_advice": "",
      "needs_review": false,
      "implementation_status": "structured"
    },
    {
      "id": "rogue-sneak-attack-l17",
      "slug": "rogue-sneak-attack-l17",
      "name": "rogue-sneak-attack-l17",
      "aliases": [
        "rogue-sneak-attack-l17",
        ""
      ],
      "source": "native",
      "source_bucket": "srd_or_original_summary",
      "rules_version": "5e2024-compatible",
      "class_id": "rogue",
      "subclass_id": null,
      "species_id": null,
      "feat_id": null,
      "background_id": null,
      "item_id": null,
      "level": 0,
      "kind": "class",
      "action_type": "passive",
      "activation_type": "passive",
      "trigger": "",
      "range": "",
      "duration": "",
      "concentration": false,
      "resource_name": "",
      "resource_cost": null,
      "uses_max": null,
      "uses_current": null,
      "uses_formula": "",
      "recovery": "none",
      "save_ability": "",
      "save_dc_formula": "",
      "attack_bonus_formula": "",
      "damage_formula": "",
      "healing_formula": "",
      "damage_type": "",
      "scaling": {},
      "grants_actions": [],
      "grants_spells": [],
      "grants_proficiencies": [],
      "grants_resistances": [],
      "grants_immunities": [],
      "grants_senses": [],
      "grants_movement": {},
      "grants_ac_formula": "",
      "grants_stat_override": {},
      "grants_advantage": [],
      "grants_disadvantage": [],
      "roll_buttons": [],
      "runtime_hooks": [],
      "safe_summary": "Your Sneak Attack damage increases to 9d6.",
      "rules_summary": "Your Sneak Attack damage increases to 9d6.",
      "play_advice": "",
      "needs_review": false,
      "implementation_status": "structured"
    },
    {
      "id": "rogue-sneak-attack-l19",
      "slug": "rogue-sneak-attack-l19",
      "name": "rogue-sneak-attack-l19",
      "aliases": [
        "rogue-sneak-attack-l19",
        ""
      ],
      "source": "native",
      "source_bucket": "srd_or_original_summary",
      "rules_version": "5e2024-compatible",
      "class_id": "rogue",
      "subclass_id": null,
      "species_id": null,
      "feat_id": null,
      "background_id": null,
      "item_id": null,
      "level": 0,
      "kind": "class",
      "action_type": "passive",
      "activation_type": "passive",
      "trigger": "",
      "range": "",
      "duration": "",
      "concentration": false,
      "resource_name": "",
      "resource_cost": null,
      "uses_max": null,
      "uses_current": null,
      "uses_formula": "",
      "recovery": "none",
      "save_ability": "",
      "save_dc_formula": "",
      "attack_bonus_formula": "",
      "damage_formula": "",
      "healing_formula": "",
      "damage_type": "",
      "scaling": {},
      "grants_actions": [],
      "grants_spells": [],
      "grants_proficiencies": [],
      "grants_resistances": [],
      "grants_immunities": [],
      "grants_senses": [],
      "grants_movement": {},
      "grants_ac_formula": "",
      "grants_stat_override": {},
      "grants_advantage": [],
      "grants_disadvantage": [],
      "roll_buttons": [],
      "runtime_hooks": [],
      "safe_summary": "Your Sneak Attack damage increases to 10d6.",
      "rules_summary": "Your Sneak Attack damage increases to 10d6.",
      "play_advice": "",
      "needs_review": false,
      "implementation_status": "structured"
    },
    {
      "id": "rogue-sneak-attack-l20",
      "slug": "rogue-sneak-attack-l20",
      "name": "rogue-sneak-attack-l20",
      "aliases": [
        "rogue-sneak-attack-l20",
        ""
      ],
      "source": "native",
      "source_bucket": "srd_or_original_summary",
      "rules_version": "5e2024-compatible",
      "class_id": "rogue",
      "subclass_id": null,
      "species_id": null,
      "feat_id": null,
      "background_id": null,
      "item_id": null,
      "level": 0,
      "kind": "class",
      "action_type": "passive",
      "activation_type": "passive",
      "trigger": "",
      "range": "",
      "duration": "",
      "concentration": false,
      "resource_name": "",
      "resource_cost": null,
      "uses_max": null,
      "uses_current": null,
      "uses_formula": "",
      "recovery": "none",
      "save_ability": "",
      "save_dc_formula": "",
      "attack_bonus_formula": "",
      "damage_formula": "",
      "healing_formula": "",
      "damage_type": "",
      "scaling": {},
      "grants_actions": [],
      "grants_spells": [],
      "grants_proficiencies": [],
      "grants_resistances": [],
      "grants_immunities": [],
      "grants_senses": [],
      "grants_movement": {},
      "grants_ac_formula": "",
      "grants_stat_override": {},
      "grants_advantage": [],
      "grants_disadvantage": [],
      "roll_buttons": [],
      "runtime_hooks": [],
      "safe_summary": "Your Sneak Attack damage remains at 10d6 at level 20.",
      "rules_summary": "Your Sneak Attack damage remains at 10d6 at level 20.",
      "play_advice": "",
      "needs_review": false,
      "implementation_status": "structured"
    },
    {
      "id": "rogue-ability-score-improvement-l4",
      "slug": "rogue-ability-score-improvement-l4",
      "name": "rogue-ability-score-improvement-l4",
      "aliases": [
        "rogue-ability-score-improvement-l4",
        ""
      ],
      "source": "native",
      "source_bucket": "srd_or_original_summary",
      "rules_version": "5e2024-compatible",
      "class_id": "rogue",
      "subclass_id": null,
      "species_id": null,
      "feat_id": null,
      "background_id": null,
      "item_id": null,
      "level": 0,
      "kind": "class",
      "action_type": "passive",
      "activation_type": "passive",
      "trigger": "",
      "range": "",
      "duration": "",
      "concentration": false,
      "resource_name": "",
      "resource_cost": null,
      "uses_max": null,
      "uses_current": null,
      "uses_formula": "",
      "recovery": "none",
      "save_ability": "",
      "save_dc_formula": "",
      "attack_bonus_formula": "",
      "damage_formula": "",
      "healing_formula": "",
      "damage_type": "",
      "scaling": {},
      "grants_actions": [],
      "grants_spells": [],
      "grants_proficiencies": [],
      "grants_resistances": [],
      "grants_immunities": [],
      "grants_senses": [],
      "grants_movement": {},
      "grants_ac_formula": "",
      "grants_stat_override": {},
      "grants_advantage": [],
      "grants_disadvantage": [],
      "roll_buttons": [],
      "runtime_hooks": [],
      "safe_summary": "Increase one ability score by 2, or two ability scores by 1 each, or gain a feat.",
      "rules_summary": "Increase one ability score by 2, or two ability scores by 1 each, or gain a feat.",
      "play_advice": "",
      "needs_review": false,
      "implementation_status": "structured"
    },
    {
      "id": "rogue-ability-score-improvement-l8",
      "slug": "rogue-ability-score-improvement-l8",
      "name": "rogue-ability-score-improvement-l8",
      "aliases": [
        "rogue-ability-score-improvement-l8",
        ""
      ],
      "source": "native",
      "source_bucket": "srd_or_original_summary",
      "rules_version": "5e2024-compatible",
      "class_id": "rogue",
      "subclass_id": null,
      "species_id": null,
      "feat_id": null,
      "background_id": null,
      "item_id": null,
      "level": 0,
      "kind": "class",
      "action_type": "passive",
      "activation_type": "passive",
      "trigger": "",
      "range": "",
      "duration": "",
      "concentration": false,
      "resource_name": "",
      "resource_cost": null,
      "uses_max": null,
      "uses_current": null,
      "uses_formula": "",
      "recovery": "none",
      "save_ability": "",
      "save_dc_formula": "",
      "attack_bonus_formula": "",
      "damage_formula": "",
      "healing_formula": "",
      "damage_type": "",
      "scaling": {},
      "grants_actions": [],
      "grants_spells": [],
      "grants_proficiencies": [],
      "grants_resistances": [],
      "grants_immunities": [],
      "grants_senses": [],
      "grants_movement": {},
      "grants_ac_formula": "",
      "grants_stat_override": {},
      "grants_advantage": [],
      "grants_disadvantage": [],
      "roll_buttons": [],
      "runtime_hooks": [],
      "safe_summary": "Increase one ability score by 2, or two ability scores by 1 each, or gain a feat.",
      "rules_summary": "Increase one ability score by 2, or two ability scores by 1 each, or gain a feat.",
      "play_advice": "",
      "needs_review": false,
      "implementation_status": "structured"
    },
    {
      "id": "rogue-ability-score-improvement-l12",
      "slug": "rogue-ability-score-improvement-l12",
      "name": "rogue-ability-score-improvement-l12",
      "aliases": [
        "rogue-ability-score-improvement-l12",
        ""
      ],
      "source": "native",
      "source_bucket": "srd_or_original_summary",
      "rules_version": "5e2024-compatible",
      "class_id": "rogue",
      "subclass_id": null,
      "species_id": null,
      "feat_id": null,
      "background_id": null,
      "item_id": null,
      "level": 0,
      "kind": "class",
      "action_type": "passive",
      "activation_type": "passive",
      "trigger": "",
      "range": "",
      "duration": "",
      "concentration": false,
      "resource_name": "",
      "resource_cost": null,
      "uses_max": null,
      "uses_current": null,
      "uses_formula": "",
      "recovery": "none",
      "save_ability": "",
      "save_dc_formula": "",
      "attack_bonus_formula": "",
      "damage_formula": "",
      "healing_formula": "",
      "damage_type": "",
      "scaling": {},
      "grants_actions": [],
      "grants_spells": [],
      "grants_proficiencies": [],
      "grants_resistances": [],
      "grants_immunities": [],
      "grants_senses": [],
      "grants_movement": {},
      "grants_ac_formula": "",
      "grants_stat_override": {},
      "grants_advantage": [],
      "grants_disadvantage": [],
      "roll_buttons": [],
      "runtime_hooks": [],
      "safe_summary": "Increase one ability score by 2, or two ability scores by 1 each, or gain a feat.",
      "rules_summary": "Increase one ability score by 2, or two ability scores by 1 each, or gain a feat.",
      "play_advice": "",
      "needs_review": false,
      "implementation_status": "structured"
    },
    {
      "id": "rogue-ability-score-improvement-l16",
      "slug": "rogue-ability-score-improvement-l16",
      "name": "rogue-ability-score-improvement-l16",
      "aliases": [
        "rogue-ability-score-improvement-l16",
        ""
      ],
      "source": "native",
      "source_bucket": "srd_or_original_summary",
      "rules_version": "5e2024-compatible",
      "class_id": "rogue",
      "subclass_id": null,
      "species_id": null,
      "feat_id": null,
      "background_id": null,
      "item_id": null,
      "level": 0,
      "kind": "class",
      "action_type": "passive",
      "activation_type": "passive",
      "trigger": "",
      "range": "",
      "duration": "",
      "concentration": false,
      "resource_name": "",
      "resource_cost": null,
      "uses_max": null,
      "uses_current": null,
      "uses_formula": "",
      "recovery": "none",
      "save_ability": "",
      "save_dc_formula": "",
      "attack_bonus_formula": "",
      "damage_formula": "",
      "healing_formula": "",
      "damage_type": "",
      "scaling": {},
      "grants_actions": [],
      "grants_spells": [],
      "grants_proficiencies": [],
      "grants_resistances": [],
      "grants_immunities": [],
      "grants_senses": [],
      "grants_movement": {},
      "grants_ac_formula": "",
      "grants_stat_override": {},
      "grants_advantage": [],
      "grants_disadvantage": [],
      "roll_buttons": [],
      "runtime_hooks": [],
      "safe_summary": "Increase one ability score by 2, or two ability scores by 1 each, or gain a feat.",
      "rules_summary": "Increase one ability score by 2, or two ability scores by 1 each, or gain a feat.",
      "play_advice": "",
      "needs_review": false,
      "implementation_status": "structured"
    },
    {
      "id": "rogue-subclass-feature-l10",
      "slug": "rogue-subclass-feature-l10",
      "name": "rogue-subclass-feature-l10",
      "aliases": [
        "rogue-subclass-feature-l10",
        ""
      ],
      "source": "native",
      "source_bucket": "srd_or_original_summary",
      "rules_version": "5e2024-compatible",
      "class_id": "rogue",
      "subclass_id": null,
      "species_id": null,
      "feat_id": null,
      "background_id": null,
      "item_id": null,
      "level": 0,
      "kind": "class",
      "action_type": "passive",
      "activation_type": "passive",
      "trigger": "",
      "range": "",
      "duration": "",
      "concentration": false,
      "resource_name": "",
      "resource_cost": null,
      "uses_max": null,
      "uses_current": null,
      "uses_formula": "",
      "recovery": "none",
      "save_ability": "",
      "save_dc_formula": "",
      "attack_bonus_formula": "",
      "damage_formula": "",
      "healing_formula": "",
      "damage_type": "",
      "scaling": {},
      "grants_actions": [],
      "grants_spells": [],
      "grants_proficiencies": [],
      "grants_resistances": [],
      "grants_immunities": [],
      "grants_senses": [],
      "grants_movement": {},
      "grants_ac_formula": "",
      "grants_stat_override": {},
      "grants_advantage": [],
      "grants_disadvantage": [],
      "roll_buttons": [],
      "runtime_hooks": [],
      "safe_summary": "Your Roguish Archetype grants you an additional feature at level 10.",
      "rules_summary": "Your Roguish Archetype grants you an additional feature at level 10.",
      "play_advice": "",
      "needs_review": false,
      "implementation_status": "structured"
    },
    {
      "id": "rogue-subclass-feature-l14",
      "slug": "rogue-subclass-feature-l14",
      "name": "rogue-subclass-feature-l14",
      "aliases": [
        "rogue-subclass-feature-l14",
        ""
      ],
      "source": "native",
      "source_bucket": "srd_or_original_summary",
      "rules_version": "5e2024-compatible",
      "class_id": "rogue",
      "subclass_id": null,
      "species_id": null,
      "feat_id": null,
      "background_id": null,
      "item_id": null,
      "level": 0,
      "kind": "class",
      "action_type": "passive",
      "activation_type": "passive",
      "trigger": "",
      "range": "",
      "duration": "",
      "concentration": false,
      "resource_name": "",
      "resource_cost": null,
      "uses_max": null,
      "uses_current": null,
      "uses_formula": "",
      "recovery": "none",
      "save_ability": "",
      "save_dc_formula": "",
      "attack_bonus_formula": "",
      "damage_formula": "",
      "healing_formula": "",
      "damage_type": "",
      "scaling": {},
      "grants_actions": [],
      "grants_spells": [],
      "grants_proficiencies": [],
      "grants_resistances": [],
      "grants_immunities": [],
      "grants_senses": [],
      "grants_movement": {},
      "grants_ac_formula": "",
      "grants_stat_override": {},
      "grants_advantage": [],
      "grants_disadvantage": [],
      "roll_buttons": [],
      "runtime_hooks": [],
      "safe_summary": "Your Roguish Archetype grants you an additional feature at level 14.",
      "rules_summary": "Your Roguish Archetype grants you an additional feature at level 14.",
      "play_advice": "",
      "needs_review": false,
      "implementation_status": "structured"
    },
    {
      "id": "rogue-subclass-feature-l15",
      "slug": "rogue-subclass-feature-l15",
      "name": "rogue-subclass-feature-l15",
      "aliases": [
        "rogue-subclass-feature-l15",
        ""
      ],
      "source": "native",
      "source_bucket": "srd_or_original_summary",
      "rules_version": "5e2024-compatible",
      "class_id": "rogue",
      "subclass_id": null,
      "species_id": null,
      "feat_id": null,
      "background_id": null,
      "item_id": null,
      "level": 0,
      "kind": "class",
      "action_type": "passive",
      "activation_type": "passive",
      "trigger": "",
      "range": "",
      "duration": "",
      "concentration": false,
      "resource_name": "",
      "resource_cost": null,
      "uses_max": null,
      "uses_current": null,
      "uses_formula": "",
      "recovery": "none",
      "save_ability": "",
      "save_dc_formula": "",
      "attack_bonus_formula": "",
      "damage_formula": "",
      "healing_formula": "",
      "damage_type": "",
      "scaling": {},
      "grants_actions": [],
      "grants_spells": [],
      "grants_proficiencies": [],
      "grants_resistances": [],
      "grants_immunities": [],
      "grants_senses": [],
      "grants_movement": {},
      "grants_ac_formula": "",
      "grants_stat_override": {},
      "grants_advantage": [],
      "grants_disadvantage": [],
      "roll_buttons": [],
      "runtime_hooks": [],
      "safe_summary": "Your Roguish Archetype grants you an additional feature at level 15.",
      "rules_summary": "Your Roguish Archetype grants you an additional feature at level 15.",
      "play_advice": "",
      "needs_review": false,
      "implementation_status": "structured"
    },
    {
      "id": "rogue-epic-boon-l19",
      "slug": "rogue-epic-boon-l19",
      "name": "rogue-epic-boon-l19",
      "aliases": [
        "rogue-epic-boon-l19",
        ""
      ],
      "source": "native",
      "source_bucket": "srd_or_original_summary",
      "rules_version": "5e2024-compatible",
      "class_id": "rogue",
      "subclass_id": null,
      "species_id": null,
      "feat_id": null,
      "background_id": null,
      "item_id": null,
      "level": 0,
      "kind": "class",
      "action_type": "passive",
      "activation_type": "passive",
      "trigger": "",
      "range": "",
      "duration": "",
      "concentration": false,
      "resource_name": "",
      "resource_cost": null,
      "uses_max": null,
      "uses_current": null,
      "uses_formula": "",
      "recovery": "none",
      "save_ability": "",
      "save_dc_formula": "",
      "attack_bonus_formula": "",
      "damage_formula": "",
      "healing_formula": "",
      "damage_type": "",
      "scaling": {},
      "grants_actions": [],
      "grants_spells": [],
      "grants_proficiencies": [],
      "grants_resistances": [],
      "grants_immunities": [],
      "grants_senses": [],
      "grants_movement": {},
      "grants_ac_formula": "",
      "grants_stat_override": {},
      "grants_advantage": [],
      "grants_disadvantage": [],
      "roll_buttons": [],
      "runtime_hooks": [],
      "safe_summary": "Gain an Epic Boon feat, which also increases one ability score by 1 (up to a maximum of 30).",
      "rules_summary": "Gain an Epic Boon feat, which also increases one ability score by 1 (up to a maximum of 30).",
      "play_advice": "",
      "needs_review": false,
      "implementation_status": "structured"
    },
    {
      "id": "rogue-thieves-cant",
      "slug": "thieves-cant",
      "name": "Thieves\u2019 Cant",
      "aliases": [
        "Thieves\u2019 Cant"
      ],
      "source": "original safe summary",
      "source_bucket": "stub_or_original_summary",
      "rules_version": "5e2024-compatible",
      "class_id": "rogue",
      "subclass_id": null,
      "species_id": null,
      "feat_id": null,
      "background_id": null,
      "item_id": null,
      "level": 0,
      "kind": "class",
      "action_type": "passive",
      "activation_type": "passive",
      "trigger": "",
      "range": "",
      "duration": "",
      "concentration": false,
      "resource_name": "",
      "resource_cost": null,
      "uses_max": null,
      "uses_current": null,
      "uses_formula": "",
      "recovery": "none",
      "save_ability": "",
      "save_dc_formula": "",
      "attack_bonus_formula": "",
      "damage_formula": "",
      "healing_formula": "",
      "damage_type": "",
      "scaling": {},
      "grants_actions": [],
      "grants_spells": [],
      "grants_proficiencies": [],
      "grants_resistances": [],
      "grants_immunities": [],
      "grants_senses": [],
      "grants_movement": {},
      "grants_ac_formula": "",
      "grants_stat_override": {},
      "grants_advantage": [],
      "grants_disadvantage": [],
      "roll_buttons": [],
      "runtime_hooks": [],
      "safe_summary": "Thieves\u2019 Cant is tracked as a Rogue feature. Needs table-specific rules text if your source differs.",
      "rules_summary": "Needs DM content",
      "play_advice": "",
      "needs_review": true,
      "implementation_status": "structured_stub"
    },
    {
      "id": "rogue-cunning-action",
      "slug": "cunning-action",
      "name": "Cunning Action",
      "aliases": [
        "Cunning Action"
      ],
      "source": "original safe summary",
      "source_bucket": "stub_or_original_summary",
      "rules_version": "5e2024-compatible",
      "class_id": "rogue",
      "subclass_id": null,
      "species_id": null,
      "feat_id": null,
      "background_id": null,
      "item_id": null,
      "level": 0,
      "kind": "class",
      "action_type": "passive",
      "activation_type": "passive",
      "trigger": "",
      "range": "",
      "duration": "",
      "concentration": false,
      "resource_name": "",
      "resource_cost": null,
      "uses_max": null,
      "uses_current": null,
      "uses_formula": "",
      "recovery": "none",
      "save_ability": "",
      "save_dc_formula": "",
      "attack_bonus_formula": "",
      "damage_formula": "",
      "healing_formula": "",
      "damage_type": "",
      "scaling": {},
      "grants_actions": [],
      "grants_spells": [],
      "grants_proficiencies": [],
      "grants_resistances": [],
      "grants_immunities": [],
      "grants_senses": [],
      "grants_movement": {},
      "grants_ac_formula": "",
      "grants_stat_override": {},
      "grants_advantage": [],
      "grants_disadvantage": [],
      "roll_buttons": [],
      "runtime_hooks": [],
      "safe_summary": "Cunning Action is tracked as a Rogue feature. Needs table-specific rules text if your source differs.",
      "rules_summary": "Needs DM content",
      "play_advice": "",
      "needs_review": true,
      "implementation_status": "structured_stub"
    },
    {
      "id": "rogue-steady-aim",
      "slug": "steady-aim",
      "name": "Steady Aim",
      "aliases": [
        "Steady Aim"
      ],
      "source": "original safe summary",
      "source_bucket": "stub_or_original_summary",
      "rules_version": "5e2024-compatible",
      "class_id": "rogue",
      "subclass_id": null,
      "species_id": null,
      "feat_id": null,
      "background_id": null,
      "item_id": null,
      "level": 0,
      "kind": "class",
      "action_type": "passive",
      "activation_type": "passive",
      "trigger": "",
      "range": "",
      "duration": "",
      "concentration": false,
      "resource_name": "",
      "resource_cost": null,
      "uses_max": null,
      "uses_current": null,
      "uses_formula": "",
      "recovery": "none",
      "save_ability": "",
      "save_dc_formula": "",
      "attack_bonus_formula": "",
      "damage_formula": "",
      "healing_formula": "",
      "damage_type": "",
      "scaling": {},
      "grants_actions": [],
      "grants_spells": [],
      "grants_proficiencies": [],
      "grants_resistances": [],
      "grants_immunities": [],
      "grants_senses": [],
      "grants_movement": {},
      "grants_ac_formula": "",
      "grants_stat_override": {},
      "grants_advantage": [],
      "grants_disadvantage": [],
      "roll_buttons": [],
      "runtime_hooks": [],
      "safe_summary": "Steady Aim is tracked as a Rogue feature. Needs table-specific rules text if your source differs.",
      "rules_summary": "Needs DM content",
      "play_advice": "",
      "needs_review": true,
      "implementation_status": "structured_stub"
    },
    {
      "id": "rogue-uncanny-dodge",
      "slug": "uncanny-dodge",
      "name": "Uncanny Dodge",
      "aliases": [
        "Uncanny Dodge"
      ],
      "source": "original safe summary",
      "source_bucket": "stub_or_original_summary",
      "rules_version": "5e2024-compatible",
      "class_id": "rogue",
      "subclass_id": null,
      "species_id": null,
      "feat_id": null,
      "background_id": null,
      "item_id": null,
      "level": 0,
      "kind": "class",
      "action_type": "passive",
      "activation_type": "passive",
      "trigger": "",
      "range": "",
      "duration": "",
      "concentration": false,
      "resource_name": "",
      "resource_cost": null,
      "uses_max": null,
      "uses_current": null,
      "uses_formula": "",
      "recovery": "none",
      "save_ability": "",
      "save_dc_formula": "",
      "attack_bonus_formula": "",
      "damage_formula": "",
      "healing_formula": "",
      "damage_type": "",
      "scaling": {},
      "grants_actions": [],
      "grants_spells": [],
      "grants_proficiencies": [],
      "grants_resistances": [],
      "grants_immunities": [],
      "grants_senses": [],
      "grants_movement": {},
      "grants_ac_formula": "",
      "grants_stat_override": {},
      "grants_advantage": [],
      "grants_disadvantage": [],
      "roll_buttons": [],
      "runtime_hooks": [],
      "safe_summary": "Uncanny Dodge is tracked as a Rogue feature. Needs table-specific rules text if your source differs.",
      "rules_summary": "Needs DM content",
      "play_advice": "",
      "needs_review": true,
      "implementation_status": "structured_stub"
    },
    {
      "id": "rogue-reliable-talent",
      "slug": "reliable-talent",
      "name": "Reliable Talent",
      "aliases": [
        "Reliable Talent"
      ],
      "source": "original safe summary",
      "source_bucket": "stub_or_original_summary",
      "rules_version": "5e2024-compatible",
      "class_id": "rogue",
      "subclass_id": null,
      "species_id": null,
      "feat_id": null,
      "background_id": null,
      "item_id": null,
      "level": 0,
      "kind": "class",
      "action_type": "passive",
      "activation_type": "passive",
      "trigger": "",
      "range": "",
      "duration": "",
      "concentration": false,
      "resource_name": "",
      "resource_cost": null,
      "uses_max": null,
      "uses_current": null,
      "uses_formula": "",
      "recovery": "none",
      "save_ability": "",
      "save_dc_formula": "",
      "attack_bonus_formula": "",
      "damage_formula": "",
      "healing_formula": "",
      "damage_type": "",
      "scaling": {},
      "grants_actions": [],
      "grants_spells": [],
      "grants_proficiencies": [],
      "grants_resistances": [],
      "grants_immunities": [],
      "grants_senses": [],
      "grants_movement": {},
      "grants_ac_formula": "",
      "grants_stat_override": {},
      "grants_advantage": [],
      "grants_disadvantage": [],
      "roll_buttons": [],
      "runtime_hooks": [],
      "safe_summary": "Reliable Talent is tracked as a Rogue feature. Needs table-specific rules text if your source differs.",
      "rules_summary": "Needs DM content",
      "play_advice": "",
      "needs_review": true,
      "implementation_status": "structured_stub"
    },
    {
      "id": "rogue-blindsense",
      "slug": "blindsense",
      "name": "Blindsense",
      "aliases": [
        "Blindsense"
      ],
      "source": "original safe summary",
      "source_bucket": "stub_or_original_summary",
      "rules_version": "5e2024-compatible",
      "class_id": "rogue",
      "subclass_id": null,
      "species_id": null,
      "feat_id": null,
      "background_id": null,
      "item_id": null,
      "level": 0,
      "kind": "class",
      "action_type": "passive",
      "activation_type": "passive",
      "trigger": "",
      "range": "",
      "duration": "",
      "concentration": false,
      "resource_name": "",
      "resource_cost": null,
      "uses_max": null,
      "uses_current": null,
      "uses_formula": "",
      "recovery": "none",
      "save_ability": "",
      "save_dc_formula": "",
      "attack_bonus_formula": "",
      "damage_formula": "",
      "healing_formula": "",
      "damage_type": "",
      "scaling": {},
      "grants_actions": [],
      "grants_spells": [],
      "grants_proficiencies": [],
      "grants_resistances": [],
      "grants_immunities": [],
      "grants_senses": [],
      "grants_movement": {},
      "grants_ac_formula": "",
      "grants_stat_override": {},
      "grants_advantage": [],
      "grants_disadvantage": [],
      "roll_buttons": [],
      "runtime_hooks": [],
      "safe_summary": "Blindsense is tracked as a Rogue feature. Needs table-specific rules text if your source differs.",
      "rules_summary": "Needs DM content",
      "play_advice": "",
      "needs_review": true,
      "implementation_status": "structured_stub"
    },
    {
      "id": "rogue-slippery-mind",
      "slug": "slippery-mind",
      "name": "Slippery Mind",
      "aliases": [
        "Slippery Mind"
      ],
      "source": "original safe summary",
      "source_bucket": "stub_or_original_summary",
      "rules_version": "5e2024-compatible",
      "class_id": "rogue",
      "subclass_id": null,
      "species_id": null,
      "feat_id": null,
      "background_id": null,
      "item_id": null,
      "level": 0,
      "kind": "class",
      "action_type": "passive",
      "activation_type": "passive",
      "trigger": "",
      "range": "",
      "duration": "",
      "concentration": false,
      "resource_name": "",
      "resource_cost": null,
      "uses_max": null,
      "uses_current": null,
      "uses_formula": "",
      "recovery": "none",
      "save_ability": "",
      "save_dc_formula": "",
      "attack_bonus_formula": "",
      "damage_formula": "",
      "healing_formula": "",
      "damage_type": "",
      "scaling": {},
      "grants_actions": [],
      "grants_spells": [],
      "grants_proficiencies": [],
      "grants_resistances": [],
      "grants_immunities": [],
      "grants_senses": [],
      "grants_movement": {},
      "grants_ac_formula": "",
      "grants_stat_override": {},
      "grants_advantage": [],
      "grants_disadvantage": [],
      "roll_buttons": [],
      "runtime_hooks": [],
      "safe_summary": "Slippery Mind is tracked as a Rogue feature. Needs table-specific rules text if your source differs.",
      "rules_summary": "Needs DM content",
      "play_advice": "",
      "needs_review": true,
      "implementation_status": "structured_stub"
    },
    {
      "id": "rogue-stroke-of-luck",
      "slug": "stroke-of-luck",
      "name": "Stroke of Luck",
      "aliases": [
        "Stroke of Luck"
      ],
      "source": "original safe summary",
      "source_bucket": "stub_or_original_summary",
      "rules_version": "5e2024-compatible",
      "class_id": "rogue",
      "subclass_id": null,
      "species_id": null,
      "feat_id": null,
      "background_id": null,
      "item_id": null,
      "level": 0,
      "kind": "class",
      "action_type": "passive",
      "activation_type": "passive",
      "trigger": "",
      "range": "",
      "duration": "",
      "concentration": false,
      "resource_name": "",
      "resource_cost": null,
      "uses_max": null,
      "uses_current": null,
      "uses_formula": "",
      "recovery": "none",
      "save_ability": "",
      "save_dc_formula": "",
      "attack_bonus_formula": "",
      "damage_formula": "",
      "healing_formula": "",
      "damage_type": "",
      "scaling": {},
      "grants_actions": [],
      "grants_spells": [],
      "grants_proficiencies": [],
      "grants_resistances": [],
      "grants_immunities": [],
      "grants_senses": [],
      "grants_movement": {},
      "grants_ac_formula": "",
      "grants_stat_override": {},
      "grants_advantage": [],
      "grants_disadvantage": [],
      "roll_buttons": [],
      "runtime_hooks": [],
      "safe_summary": "Stroke of Luck is tracked as a Rogue feature. Needs table-specific rules text if your source differs.",
      "rules_summary": "Needs DM content",
      "play_advice": "",
      "needs_review": true,
      "implementation_status": "structured_stub"
    }
  ]
}